reexport/__init__.py
reexport/_core.py
reexport-0.1.0.dist-info/LICENSE
reexport-0.1.0.dist-info/METADATA
reexport-0.1.0.dist-info/WHEEL
reexport-0.1.0.dist-info/RECORD
