Metadata-Version: 2.1
Name: reexport
Version: 0.1.0
Summary: reexport provides a simple way to re-export objects.
Author: ZhengYu, Xu
Author-email: zen-xu@outlook.com
Requires-Python: >=3.8,<4.0
Classifier: License :: OSI Approved :: MIT License
Classifier: Programming Language :: Python :: 3
Classifier: Programming Language :: Python :: 3.8
Classifier: Programming Language :: Python :: 3.9
Classifier: Programming Language :: Python :: 3.10
Classifier: Programming Language :: Python :: 3.11
Classifier: Programming Language :: Python :: 3.12
Classifier: Programming Language :: Python :: 3 :: Only
Requires-Dist: typing-extensions (>=4.6.1) ; python_version < "3.10"
